azure/mgmt/scheduler/__init__.py
azure/mgmt/scheduler/patch.py
azure/mgmt/scheduler/scheduler_management_client.py
azure/mgmt/scheduler/version.py
azure/mgmt/scheduler/models/__init__.py
azure/mgmt/scheduler/models/basic_authentication.py
azure/mgmt/scheduler/models/client_cert_authentication.py
azure/mgmt/scheduler/models/http_authentication.py
azure/mgmt/scheduler/models/http_request.py
azure/mgmt/scheduler/models/job_action.py
azure/mgmt/scheduler/models/job_collection_definition.py
azure/mgmt/scheduler/models/job_collection_definition_paged.py
azure/mgmt/scheduler/models/job_collection_properties.py
azure/mgmt/scheduler/models/job_collection_quota.py
azure/mgmt/scheduler/models/job_definition.py
azure/mgmt/scheduler/models/job_definition_paged.py
azure/mgmt/scheduler/models/job_error_action.py
azure/mgmt/scheduler/models/job_history_definition.py
azure/mgmt/scheduler/models/job_history_definition_paged.py
azure/mgmt/scheduler/models/job_history_definition_properties.py
azure/mgmt/scheduler/models/job_history_filter.py
azure/mgmt/scheduler/models/job_max_recurrence.py
azure/mgmt/scheduler/models/job_properties.py
azure/mgmt/scheduler/models/job_recurrence.py
azure/mgmt/scheduler/models/job_recurrence_schedule.py
azure/mgmt/scheduler/models/job_recurrence_schedule_monthly_occurrence.py
azure/mgmt/scheduler/models/job_state_filter.py
azure/mgmt/scheduler/models/job_status.py
azure/mgmt/scheduler/models/oauth_authentication.py
azure/mgmt/scheduler/models/retry_policy.py
azure/mgmt/scheduler/models/scheduler_management_client_enums.py
azure/mgmt/scheduler/models/service_bus_authentication.py
azure/mgmt/scheduler/models/service_bus_brokered_message_properties.py
azure/mgmt/scheduler/models/service_bus_message.py
azure/mgmt/scheduler/models/service_bus_queue_message.py
azure/mgmt/scheduler/models/service_bus_topic_message.py
azure/mgmt/scheduler/models/sku.py
azure/mgmt/scheduler/models/storage_queue_message.py
azure_mgmt_scheduler-1.1.3.dist-info/DESCRIPTION.rst
azure_mgmt_scheduler-1.1.3.dist-info/METADATA
azure_mgmt_scheduler-1.1.3.dist-info/RECORD
azure_mgmt_scheduler-1.1.3.dist-info/WHEEL
azure_mgmt_scheduler-1.1.3.dist-info/metadata.json
azure_mgmt_scheduler-1.1.3.dist-info/top_level.txt
